dogecloud_uploader/__init__.py
dogecloud_uploader/cli.py
dogecloud_uploader/client.py
dogecloud_uploader/exceptions.py
dogecloud_uploader/utils.py
dogecloud_uploader-1.1.0.dist-info/licenses/LICENSE
dogecloud_uploader-1.1.0.dist-info/METADATA
dogecloud_uploader-1.1.0.dist-info/WHEEL
dogecloud_uploader-1.1.0.dist-info/entry_points.txt
dogecloud_uploader-1.1.0.dist-info/top_level.txt
dogecloud_uploader-1.1.0.dist-info/RECORD
