Metadata-Version: 2.4
Name: dogecloud-uploader
Version: 1.1.0
Summary: 多吉云上传工具 - 支持图片和文件上传到多吉云存储
Author-email: Overseas Report Team <overseas.report@example.com>
Maintainer-email: Overseas Report Team <overseas.report@example.com>
License-Expression: MIT
Project-URL: Homepage, https://github.com/overseas-report/dogecloud-uploader
Project-URL: Bug Reports, https://github.com/overseas-report/dogecloud-uploader/issues
Project-URL: Source, https://github.com/overseas-report/dogecloud-uploader
Project-URL: Documentation, https://github.com/overseas-report/dogecloud-uploader#readme
Keywords: dogecloud,upload,storage,image,file
Classifier: Development Status :: 5 - Production/Stable
Classifier: Intended Audience :: Developers
Classifier: Operating System :: OS Independent
Classifier: Programming Language :: Python :: 3
Classifier: Programming Language :: Python :: 3.8
Classifier: Programming Language :: Python :: 3.9
Classifier: Programming Language :: Python :: 3.10
Classifier: Programming Language :: Python :: 3.11
Classifier: Programming Language :: Python :: 3.12
Classifier: Topic :: Internet :: WWW/HTTP
Classifier: Topic :: Software Development :: Libraries :: Python Modules
Classifier: Topic :: System :: Archiving
Requires-Python: >=3.8
License-File: LICENSE
Requires-Dist: requests>=2.31.0
Requires-Dist: python-dotenv>=1.0.0
Requires-Dist: boto3>=1.34.0
Requires-Dist: botocore>=1.34.0
Requires-Dist: aiohttp>=3.9.0
Requires-Dist: click>=8.0.0
Requires-Dist: Pillow>=10.0.0
Provides-Extra: dev
Requires-Dist: pytest>=7.0.0; extra == "dev"
Requires-Dist: pytest-asyncio>=0.21.0; extra == "dev"
Requires-Dist: pytest-cov>=4.0.0; extra == "dev"
Requires-Dist: black>=23.0.0; extra == "dev"
Requires-Dist: isort>=5.12.0; extra == "dev"
Requires-Dist: flake8>=6.0.0; extra == "dev"
Requires-Dist: mypy>=1.0.0; extra == "dev"
Requires-Dist: types-requests>=2.31.0; extra == "dev"
Provides-Extra: test
Requires-Dist: pytest>=7.0.0; extra == "test"
Requires-Dist: pytest-asyncio>=0.21.0; extra == "test"
Requires-Dist: pytest-cov>=4.0.0; extra == "test"
Dynamic: license-file
